{
    "1": [
        {
            "points": 10,
            "reason": "Молодцы",
            "admin_id": 804636463,
            "timestamp": "2025-02-11T12:30:49.605256"
        },
        {
            "points": -2,
            "reason": "Автоматическое снятие баллов за пропуск занятия",
            "admin_id": 804636463,
            "timestamp": "2025-02-11T12:41:04.916843"
        },
        {
            "points": -2,
            "reason": "Автоматическое снятие баллов за пропуск занятия",
            "admin_id": 804636463,
            "timestamp": "2025-02-11T12:42:34.670742"
        },
        {
            "points": -2,
            "reason": "Автоматическое снятие баллов за пропуск занятия",
            "admin_id": 804636463,
            "timestamp": "2025-02-11T12:43:05.639139"
        },
        {
            "points": -2,
            "reason": "Автоматическое снятие баллов за пропуск занятия",
            "admin_id": 804636463,
            "timestamp": "2025-02-11T12:45:29.760798"
        },
        {
            "points": 100,
            "reason": "100",
            "admin_id": 804636463,
            "timestamp": "2025-02-11T13:04:34.205009"
        },
        {
            "points": -2,
            "reason": "Автоматическое снятие баллов за пропуск занятия",
            "admin_id": 804636463,
            "timestamp": "2025-02-11T13:10:23.499135"
        },
        {
            "points": -2,
            "reason": "Автоматическое снятие баллов за пропуск занятия",
            "admin_id": 804636463,
            "timestamp": "2025-02-11T13:14:01.455080"
        },
        {
            "points": -2,
            "reason": "Автоматическое снятие баллов за пропуск занятия",
            "admin_id": 804636463,
            "timestamp": "2025-02-11T13:23:17.855538"
        },
        {
            "points": -2,
            "reason": "Автоматическое снятие баллов за пропуск занятия",
            "admin_id": 804636463,
            "timestamp": "2025-02-11T13:23:47.893895"
        },
        {
            "points": -2,
            "reason": "Автоматическое снятие баллов за пропуск занятия",
            "admin_id": 804636463,
            "timestamp": "2025-02-11T13:26:10.261672"
        },
        {
            "points": -2,
            "reason": "Автоматическое снятие баллов за пропуск занятия",
            "admin_id": 804636463,
            "timestamp": "2025-02-11T13:26:22.875185"
        },
        {
            "points": -2,
            "reason": "Автоматическое снятие баллов за пропуск занятия",
            "admin_id": 804636463,
            "timestamp": "2025-02-11T13:27:24.190491"
        },
        {
            "points": -2,
            "reason": "Автоматическое снятие баллов за пропуск занятия",
            "admin_id": 804636463,
            "timestamp": "2025-02-11T13:29:56.436019"
        },
        {
            "points": -2,
            "reason": "Автоматическое снятие баллов за пропуск занятия",
            "admin_id": 804636463,
            "timestamp": "2025-02-11T13:32:41.374389"
        },
        {
            "points": -2,
            "reason": "Автоматическое снятие баллов за пропуск занятия",
            "admin_id": 804636463,
            "timestamp": "2025-02-11T13:34:55.762422"
        },
        {
            "points": -2,
            "reason": "Автоматическое снятие баллов за пропуск занятия",
            "admin_id": 804636463,
            "timestamp": "2025-02-11T13:35:34.246991"
        },
        {
            "points": -2,
            "reason": "Автоматическое снятие баллов за пропуск занятия",
            "admin_id": 804636463,
            "timestamp": "2025-02-11T13:39:24.870217"
        },
        {
            "points": -2,
            "reason": "Автоматическое снятие баллов за пропуск занятия",
            "admin_id": 804636463,
            "timestamp": "2025-02-11T13:40:43.038776"
        },
        {
            "points": -2,
            "reason": "Автоматическое снятие баллов за пропуск занятия",
            "admin_id": 804636463,
            "timestamp": "2025-02-11T13:40:55.422233"
        },
        {
            "points": -2,
            "reason": "Автоматическое снятие баллов за пропуск занятия",
            "admin_id": 804636463,
            "timestamp": "2025-02-11T13:43:08.631224"
        },
        {
            "points": -2,
            "reason": "Автоматическое снятие баллов за пропуск занятия",
            "admin_id": 804636463,
            "timestamp": "2025-02-11T13:43:49.095411"
        },
        {
            "points": -2,
            "reason": "Автоматическое снятие баллов за пропуск занятия",
            "admin_id": 804636463,
            "timestamp": "2025-02-11T13:44:48.607143"
        },
        {
            "points": -2,
            "reason": "Автоматическое снятие баллов за пропуск занятия",
            "admin_id": 804636463,
            "timestamp": "2025-02-11T13:45:00.043205"
        },
        {
            "points": -2,
            "reason": "Автоматическое снятие баллов за пропуск занятия",
            "admin_id": 804636463,
            "timestamp": "2025-02-11T13:46:30.391640"
        },
        {
            "points": -2,
            "reason": "Автоматическое снятие баллов за пропуск занятия",
            "admin_id": 804636463,
            "timestamp": "2025-02-11T13:46:52.097934"
        },
        {
            "points": -2,
            "reason": "Автоматическое снятие баллов за пропуск занятия",
            "admin_id": 804636463,
            "timestamp": "2025-02-11T13:48:20.274624"
        },
        {
            "points": -2,
            "reason": "Автоматическое снятие баллов за пропуск занятия",
            "admin_id": 804636463,
            "timestamp": "2025-02-11T13:48:28.380152"
        },
        {
            "points": -2,
            "reason": "Автоматическое снятие баллов за пропуск занятия",
            "admin_id": 804636463,
            "timestamp": "2025-02-11T14:27:19.280779"
        }
    ],
    "2": [
        {
            "points": 5,
            "reason": "а",
            "admin_id": 804636463,
            "timestamp": "2025-02-11T12:32:45.696910"
        },
        {
            "points": -10,
            "reason": "вфы",
            "admin_id": 804636463,
            "timestamp": "2025-02-11T12:32:52.284254"
        },
        {
            "points": 5,
            "reason": "выф",
            "admin_id": 804636463,
            "timestamp": "2025-02-11T12:36:37.856385"
        },
        {
            "points": -2,
            "reason": "Автоматическое снятие баллов за пропуск занятия",
            "admin_id": 804636463,
            "timestamp": "2025-02-11T12:41:04.940698"
        },
        {
            "points": -2,
            "reason": "Автоматическое снятие баллов за пропуск занятия",
            "admin_id": 804636463,
            "timestamp": "2025-02-11T12:42:34.691349"
        },
        {
            "points": -2,
            "reason": "Автоматическое снятие баллов за пропуск занятия",
            "admin_id": 804636463,
            "timestamp": "2025-02-11T12:43:05.658459"
        },
        {
            "points": -2,
            "reason": "Автоматическое снятие баллов за пропуск занятия",
            "admin_id": 804636463,
            "timestamp": "2025-02-11T12:45:29.782409"
        },
        {
            "points": -2,
            "reason": "Автоматическое снятие баллов за пропуск занятия",
            "admin_id": 804636463,
            "timestamp": "2025-02-11T12:53:23.623323"
        },
        {
            "points": -2,
            "reason": "Автоматическое снятие баллов за пропуск занятия",
            "admin_id": 804636463,
            "timestamp": "2025-02-11T12:53:37.676338"
        },
        {
            "points": -2,
            "reason": "Автоматическое снятие баллов за пропуск занятия",
            "admin_id": 804636463,
            "timestamp": "2025-02-11T13:23:17.878177"
        },
        {
            "points": -2,
            "reason": "Автоматическое снятие баллов за пропуск занятия",
            "admin_id": 804636463,
            "timestamp": "2025-02-11T13:23:47.914418"
        },
        {
            "points": -2,
            "reason": "Автоматическое снятие баллов за пропуск занятия",
            "admin_id": 804636463,
            "timestamp": "2025-02-11T13:26:10.287794"
        },
        {
            "points": -2,
            "reason": "Автоматическое снятие баллов за пропуск занятия",
            "admin_id": 804636463,
            "timestamp": "2025-02-11T13:26:22.898664"
        },
        {
            "points": -2,
            "reason": "Автоматическое снятие баллов за пропуск занятия",
            "admin_id": 804636463,
            "timestamp": "2025-02-11T13:27:24.211888"
        },
        {
            "points": -2,
            "reason": "Автоматическое снятие баллов за пропуск занятия",
            "admin_id": 804636463,
            "timestamp": "2025-02-11T13:32:41.395294"
        },
        {
            "points": -2,
            "reason": "Автоматическое снятие баллов за пропуск занятия",
            "admin_id": 804636463,
            "timestamp": "2025-02-11T13:34:55.782719"
        },
        {
            "points": -2,
            "reason": "Автоматическое снятие баллов за пропуск занятия",
            "admin_id": 804636463,
            "timestamp": "2025-02-11T13:39:24.895731"
        },
        {
            "points": -2,
            "reason": "Автоматическое снятие баллов за пропуск занятия",
            "admin_id": 804636463,
            "timestamp": "2025-02-11T13:40:43.069658"
        },
        {
            "points": -2,
            "reason": "Автоматическое снятие баллов за пропуск занятия",
            "admin_id": 804636463,
            "timestamp": "2025-02-11T13:40:55.451027"
        },
        {
            "points": -2,
            "reason": "Автоматическое снятие баллов за пропуск занятия",
            "admin_id": 804636463,
            "timestamp": "2025-02-11T13:43:08.673729"
        },
        {
            "points": -2,
            "reason": "Автоматическое снятие баллов за пропуск занятия",
            "admin_id": 804636463,
            "timestamp": "2025-02-11T13:43:49.123296"
        },
        {
            "points": -2,
            "reason": "Автоматическое снятие баллов за пропуск занятия",
            "admin_id": 804636463,
            "timestamp": "2025-02-11T13:44:48.634408"
        },
        {
            "points": -2,
            "reason": "Автоматическое снятие баллов за пропуск занятия",
            "admin_id": 804636463,
            "timestamp": "2025-02-11T13:45:00.073268"
        },
        {
            "points": -2,
            "reason": "Автоматическое снятие баллов за пропуск занятия",
            "admin_id": 804636463,
            "timestamp": "2025-02-11T13:46:30.422469"
        },
        {
            "points": -2,
            "reason": "Автоматическое снятие баллов за пропуск занятия",
            "admin_id": 804636463,
            "timestamp": "2025-02-11T13:46:52.123393"
        },
        {
            "points": -2,
            "reason": "Автоматическое снятие баллов за пропуск занятия",
            "admin_id": 804636463,
            "timestamp": "2025-02-11T13:48:20.303728"
        },
        {
            "points": -2,
            "reason": "Автоматическое снятие баллов за пропуск занятия",
            "admin_id": 804636463,
            "timestamp": "2025-02-11T13:48:28.411457"
        },
        {
            "points": -2,
            "reason": "Автоматическое снятие баллов за пропуск занятия",
            "admin_id": 804636463,
            "timestamp": "2025-02-11T14:27:19.336581"
        }
    ]
}